django_kelove_admin/__init__.py
django_kelove_admin/accounts/forms.py
django_kelove_admin/admin.py
django_kelove_admin/apps.py
django_kelove_admin/ckfinder/__init__.py
django_kelove_admin/ckfinder/acl.py
django_kelove_admin/ckfinder/adapter.py
django_kelove_admin/ckfinder/ckfinder.py
django_kelove_admin/ckfinder/commands.py
django_kelove_admin/ckfinder/exception.py
django_kelove_admin/ckfinder/response.py
django_kelove_admin/ckfinder/util.py
django_kelove_admin/ckfinder/views.py
django_kelove_admin/conf.py
django_kelove_admin/db/__init__.py
django_kelove_admin/db/backends/__init__.py
django_kelove_admin/db/backends/base/__init__.py
django_kelove_admin/db/backends/base/doc.py
django_kelove_admin/db/backends/mysql/__init__.py
django_kelove_admin/db/backends/mysql/base.py
django_kelove_admin/db/backends/mysql/doc.py
django_kelove_admin/db/backends/mysql/schema.py
django_kelove_admin/db/fields.py
django_kelove_admin/db/views.py
django_kelove_admin/forms/__init__.py
django_kelove_admin/forms/fields.py
django_kelove_admin/forms/widgets.py
django_kelove_admin/ip_lookup/__init__.py
django_kelove_admin/ip_lookup/data/qqwry.dat
django_kelove_admin/ip_lookup/ip_cz.py
django_kelove_admin/ip_lookup/util.py
django_kelove_admin/locale/zh_Hans/LC_MESSAGES/django.mo
django_kelove_admin/locale/zh_Hans/LC_MESSAGES/django.po
django_kelove_admin/management/__init__.py
django_kelove_admin/management/commands/__init__.py
django_kelove_admin/management/commands/superuserinit.py
django_kelove_admin/migrations/0001_initial.py
django_kelove_admin/migrations/0002_loginlog.py
django_kelove_admin/migrations/__init__.py
django_kelove_admin/models.py
django_kelove_admin/otp/__init__.py
django_kelove_admin/otp/decorators.py
django_kelove_admin/otp/device.py
django_kelove_admin/otp/forms.py
django_kelove_admin/otp/middleware.py
django_kelove_admin/otp/views.py
django_kelove_admin/settings.py
django_kelove_admin/static/kelove_admin/bootstrap4/css/bootstrap.min.css
django_kelove_admin-0.4.1.dist-info/WHEEL
django_kelove_admin-0.4.1.dist-info/METADATA
django_kelove_admin-0.4.1.dist-info/RECORD
