Metadata-Version: 2.1
Name: django-kelove-admin
Version: 0.4.1
Summary: DJANGO 后台管理 增强
Home-page: https://xqitw.coding.net/public/django-kelove-admin/django-kelove-admin/git
License: Apache-2.0
Keywords: django,django-admin,django-kelove-admin
Author: IT小强xqitw.cn
Author-email: mail@xqitw.cn
Maintainer: IT小强xqitw.cn
Maintainer-email: mail@xqitw.cn
Requires-Python: >=3.6,<4.0
Classifier: Development Status :: 3 - Alpha
Classifier: Framework :: Django :: 3.1
Classifier: Intended Audience :: Developers
Classifier: License :: OSI Approved :: Apache Software License
Classifier: Natural Language :: Chinese (Simplified)
Classifier: Programming Language :: Python :: 3
Classifier: Programming Language :: Python :: 3.6
Classifier: Programming Language :: Python :: 3.7
Classifier: Programming Language :: Python :: 3.8
Classifier: Programming Language :: Python :: 3.9
Requires-Dist: django (>=3.1,<4.0)
Requires-Dist: django-import-export (>=2.3.0,<3.0.0)
Requires-Dist: django-mptt (>=0.11.0,<0.12.0)
Requires-Dist: django-otp (>=1.0.0,<2.0.0)
Requires-Dist: django-registration (>=3.1,<4.0)
Requires-Dist: pillow (>=8.0.1,<9.0.0)
Project-URL: Documentation, https://xqitw.coding.net/public/django-kelove-admin/django-kelove-admin/git
Project-URL: Repository, https://e.coding.net/xqitw/django-kelove-admin/django-kelove-admin.git
